README.md
setup.py
pyradox/__init__.py
pyradox.egg-info/PKG-INFO
pyradox.egg-info/SOURCES.txt
pyradox.egg-info/dependency_links.txt
pyradox.egg-info/requires.txt
pyradox.egg-info/top_level.txt
pyradox/convnets/__init__.py
pyradox/convnets/densenets.py
pyradox/convnets/efficientnet.py
pyradox/convnets/inceptionnet.py
pyradox/convnets/inceptionresnet.py
pyradox/convnets/mobilenet.py
pyradox/convnets/nasnet.py
pyradox/convnets/resnet.py
pyradox/convnets/segmentation.py
pyradox/convnets/vgg.py
pyradox/convnets/xceptionnet.py
pyradox/densenets/__init__.py
pyradox/modules/__init__.py
pyradox/modules/conv_modules.py
pyradox/modules/dense_modules.py
pyradox/modules/misc_modules.py
pyradox/recnets/__init__.py
tests/__init__.py
tests/test_conv_skip_connection.py
tests/test_convolution_2d.py
tests/test_dense_net_convolution_block.py
tests/test_dense_net_transition_block.py
tests/test_dense_skip_connection.py
tests/test_densely_connected.py
tests/test_densely_connected_convolutional_network121.py
tests/test_densely_connected_convolutional_network169.py
tests/test_densely_connected_convolutional_network201.py
tests/test_densely_connected_network.py
tests/test_densely_connected_resnet.py
tests/test_efficient_net.py
tests/test_efficient_net_b0.py
tests/test_efficient_net_b1.py
tests/test_efficient_net_b2.py
tests/test_efficient_net_b3.py
tests/test_efficient_net_b4.py
tests/test_efficient_net_b5.py
tests/test_efficient_net_b6.py
tests/test_efficient_net_b7.py
tests/test_efficient_net_block.py
tests/test_generalized_dense_nets.py
tests/test_generalized_vgg.py
tests/test_generalized_xception.py
tests/test_inception_block.py
tests/test_inception_conv.py
tests/test_inception_res_net_block.py
tests/test_inception_res_net_conv_2d.py
tests/test_inception_res_net_v2.py
tests/test_inception_v3.py
tests/test_inverted_res_block.py
tests/test_mobile_net.py
tests/test_mobile_net_conv_block.py
tests/test_mobile_net_depth_wise_conv_block.py
tests/test_mobile_net_v2.py
tests/test_mobile_net_v3.py
tests/test_nas_net.py
tests/test_nas_net_large.py
tests/test_nas_net_mobile.py
tests/test_nas_net_separable_conv_block.py
tests/test_res_net.py
