Metadata-Version: 2.1
Name: pyradox
Version: 1.0.1
Summary: State of the Art Neural Networks for Deep Learning
Home-page: https://github.com/Ritvik19
Author: Ritvik Rastogi
Author-email: rastogiritvik99@gmail.com
License: UNKNOWN
Platform: UNKNOWN
Classifier: Programming Language :: Python :: 3
Classifier: License :: OSI Approved :: MIT License
Classifier: Operating System :: OS Independent
